fesenjoon/Drive.py
fesenjoon/__init__.py
fesenjoon/cli.py
fesenjoon/custom_type.py
fesenjoon/mime.py
fesenjoon-0.0.5.dist-info/LICENSE
fesenjoon-0.0.5.dist-info/METADATA
fesenjoon-0.0.5.dist-info/WHEEL
fesenjoon-0.0.5.dist-info/entry_points.txt
fesenjoon-0.0.5.dist-info/top_level.txt
fesenjoon-0.0.5.dist-info/RECORD
