Metadata-Version: 2.1
Name: fesenjoon
Version: 0.0.5
Summary: A simple multiprocessing google drive api
Author-email: Mohsen Hariri <mhariri68@gmail.com>
License: GPL-3.0 License
Keywords: google drive,google cloud,backup
Classifier: Programming Language :: Python :: 3.8
Classifier: License :: OSI Approved :: GNU General Public License v3 or later (GPLv3+)
Classifier: Operating System :: OS Independent
Requires-Python: >=3.6
License-File: LICENSE
Requires-Dist: google-api-python-client (==2.64.0)
Requires-Dist: google-auth-oauthlib (==0.5.3)
Requires-Dist: importlib-metadata ; python_version < "3.8"
Provides-Extra: dev
Requires-Dist: black (>=18.3) ; extra == 'dev'
